crzp/__init__.py
crzp/api_client.py
crzp/configuration.py
crzp/rest.py
crzp/api/__init__.py
crzp/api/developers_api.py
crzp/api/ippc_api.py
crzp/api/public_api.py
crzp/models/__init__.py
crzp/models/address.py
crzp/models/agenda_reference.py
crzp/models/agenda_subject_detail.py
crzp/models/context_role.py
crzp/models/context_subject.py
crzp/models/context_system.py
crzp/models/dictionary_reference.py
crzp/models/eu_state.py
crzp/models/geo_point.py
crzp/models/geo_point_jtsk.py
crzp/models/holder_reference.py
crzp/models/identity_document_detail.py
crzp/models/ippc_activity.py
crzp/models/irz_activity_record.py
crzp/models/irz_emissions_trading_system.py
crzp/models/irz_facilities.py
crzp/models/irz_facility_detail.py
crzp/models/irz_facility_item.py
crzp/models/irz_facility_operation_item.py
crzp/models/irz_facility_operations.py
crzp/models/irz_facility_reference.py
crzp/models/legal_entity_part.py
crzp/models/named_reference.py
crzp/models/one_of_holder_reference_role_holder.py
crzp/models/person_part.py
crzp/models/role_holder_object_type.py
crzp/models/role_holders.py
crzp/models/role_reference.py
crzp/models/ruian_reference.py
crzp/models/subject_detail.py
crzp/models/subject_reference.py
crzp/models/system_reference.py
crzp/models/system_role_context.py
crzp/models/user.py
crzp/models/user_context.py
crzp/models/user_reference.py
test/__init__.py
test/test_address.py
test/test_agenda_reference.py
test/test_agenda_subject_detail.py
test/test_context_role.py
test/test_context_subject.py
test/test_context_system.py
test/test_developers_api.py
test/test_dictionary_reference.py
test/test_eu_state.py
test/test_geo_point.py
test/test_geo_point_jtsk.py
test/test_holder_reference.py
test/test_identity_document_detail.py
test/test_ippc_activity.py
test/test_ippc_api.py
test/test_irz_activity_record.py
test/test_irz_emissions_trading_system.py
test/test_irz_facilities.py
test/test_irz_facility_detail.py
test/test_irz_facility_item.py
sysnet_crzp-1.1.0.0.dist-info/LICENSE
sysnet_crzp-1.1.0.0.dist-info/METADATA
sysnet_crzp-1.1.0.0.dist-info/WHEEL
sysnet_crzp-1.1.0.0.dist-info/top_level.txt
sysnet_crzp-1.1.0.0.dist-info/RECORD
